xmlobj/__init__.py
xmlobj/xmlmapping.py
xmlobj-1.2.2.dist-info/METADATA
xmlobj-1.2.2.dist-info/WHEEL
xmlobj-1.2.2.dist-info/top_level.txt
xmlobj-1.2.2.dist-info/RECORD
