Metadata-Version: 2.1
Name: xmlobj
Version: 1.2.2
Summary: xmlobj is simple utility to map xml file to python object
Author: Alexander Barmin
Author-email: Alexander Barmin <barmin1@mail.ru>
License: MIT
Project-URL: Homepage, https://github.com/Alek-dr/xmlobj
Classifier: Programming Language :: Python :: 3
Classifier: License :: OSI Approved :: MIT License
Classifier: Operating System :: OS Independent
Requires-Python: >=3.7
Requires-Dist: xmltodict >=0.13.0
Requires-Dist: Jinja2 >=3.1
